edpoints/__init__.py
edpoints/__main__.py
edpoints/edpoints.py
edpoints/math_utils.py
edpoints-0.2.dist-info/DESCRIPTION.rst
edpoints-0.2.dist-info/METADATA
edpoints-0.2.dist-info/RECORD
edpoints-0.2.dist-info/WHEEL
edpoints-0.2.dist-info/metadata.json
edpoints-0.2.dist-info/top_level.txt
