Metadata-Version: 2.0
Name: edpoints
Version: 0.2
Summary: Generates (almost) evenly distributed, equidistant points across a perfect sphere or the globe (in cartesian, ECEF and geodetic format)
Home-page: https://github.com/ksbg/edpoints
Author: Kevin Baumgarten
Author-email: kevin@ksbg.io
License: UNKNOWN
Download-URL: https://github.com/ksbg/edpoints/archive/0.2.tar.gz
Keywords: mathematics,geography,coordinates,equidistant,sphere,globe,earth
Platform: UNKNOWN
